{"event": "task_meta", "task_id": "T03", "meta": {"id": "T03", "anchor": "introduction", "title": "Introduction"}}
{"event": "retrieval_raw", "task_id": "T03", "source": "rubric", "top_k": 0, "model": "sentence-transformers/all-MiniLM-L6-v2"}
{"event": "retrieval_done", "task_id": "T03", "source": "rubric", "kept": 0}
{"event": "retrieval_raw", "task_id": "T03", "source": "assignment", "top_k": 0, "model": "sentence-transformers/all-MiniLM-L6-v2"}
{"event": "retrieval_done", "task_id": "T03", "source": "assignment", "kept": 0}
{"event": "retrieval_raw", "task_id": "T03", "source": "assessment", "top_k": 0, "model": "sentence-transformers/all-MiniLM-L6-v2"}
{"event": "retrieval_done", "task_id": "T03", "source": "assessment", "kept": 0}
{"event": "retrieval_raw", "task_id": "T03", "source": "user", "top_k": 0, "model": "sentence-transformers/all-MiniLM-L6-v2"}
{"event": "retrieval_done", "task_id": "T03", "source": "user", "kept": 0}
{"event": "bundle_done", "task_id": "T03", "rubric": 0, "assignment": 0, "assessment": 0, "user": 0, "consensus": 0}
{"event": "task_meta", "task_id": "T03", "meta": {"id": "T03", "anchor": "introduction", "title": "Introduction"}}
{"event": "retrieval_raw", "task_id": "T03", "source": "rubric", "top_k": 0, "model": "sentence-transformers/all-MiniLM-L6-v2"}
{"event": "retrieval_done", "task_id": "T03", "source": "rubric", "kept": 0}
{"event": "retrieval_raw", "task_id": "T03", "source": "assignment", "top_k": 0, "model": "sentence-transformers/all-MiniLM-L6-v2"}
{"event": "retrieval_done", "task_id": "T03", "source": "assignment", "kept": 0}
{"event": "retrieval_raw", "task_id": "T03", "source": "assessment", "top_k": 0, "model": "sentence-transformers/all-MiniLM-L6-v2"}
{"event": "retrieval_done", "task_id": "T03", "source": "assessment", "kept": 0}
{"event": "retrieval_raw", "task_id": "T03", "source": "user", "top_k": 0, "model": "sentence-transformers/all-MiniLM-L6-v2"}
{"event": "retrieval_done", "task_id": "T03", "source": "user", "kept": 0}
{"event": "bundle_done", "task_id": "T03", "rubric": 0, "assignment": 0, "assessment": 0, "user": 0, "consensus": 0}
{"event": "task_meta", "task_id": "T03", "meta": {"id": "T03", "anchor": "introduction", "title": "Introduction"}}
{"event": "retrieval_raw", "task_id": "T03", "source": "rubric", "top_k": 0, "model": "sentence-transformers/all-MiniLM-L6-v2"}
{"event": "retrieval_done", "task_id": "T03", "source": "rubric", "kept": 0}
{"event": "retrieval_raw", "task_id": "T03", "source": "assignment", "top_k": 0, "model": "sentence-transformers/all-MiniLM-L6-v2"}
{"event": "retrieval_done", "task_id": "T03", "source": "assignment", "kept": 0}
{"event": "retrieval_raw", "task_id": "T03", "source": "assessment", "top_k": 0, "model": "sentence-transformers/all-MiniLM-L6-v2"}
{"event": "retrieval_done", "task_id": "T03", "source": "assessment", "kept": 0}
{"event": "retrieval_raw", "task_id": "T03", "source": "user", "top_k": 0, "model": "sentence-transformers/all-MiniLM-L6-v2"}
{"event": "retrieval_done", "task_id": "T03", "source": "user", "kept": 0}
{"event": "bundle_done", "task_id": "T03", "rubric": 0, "assignment": 0, "assessment": 0, "user": 0, "consensus": 0}
{"event": "task_meta", "task_id": "T03", "meta": {"id": "T03", "anchor": "introduction", "title": "Introduction"}}
{"event": "retrieval_raw", "task_id": "T03", "source": "rubric", "top_k": 0, "model": "sentence-transformers/all-MiniLM-L6-v2"}
{"event": "retrieval_done", "task_id": "T03", "source": "rubric", "kept": 0}
{"event": "retrieval_raw", "task_id": "T03", "source": "assignment", "top_k": 0, "model": "sentence-transformers/all-MiniLM-L6-v2"}
{"event": "retrieval_done", "task_id": "T03", "source": "assignment", "kept": 0}
{"event": "retrieval_raw", "task_id": "T03", "source": "assessment", "top_k": 0, "model": "sentence-transformers/all-MiniLM-L6-v2"}
{"event": "retrieval_done", "task_id": "T03", "source": "assessment", "kept": 0}
{"event": "retrieval_raw", "task_id": "T03", "source": "user", "top_k": 0, "model": "sentence-transformers/all-MiniLM-L6-v2"}
{"event": "retrieval_done", "task_id": "T03", "source": "user", "kept": 0}
{"event": "bundle_done", "task_id": "T03", "rubric": 0, "assignment": 0, "assessment": 0, "user": 0, "consensus": 0}
{"event": "task_meta", "task_id": "T03", "meta": {"id": "T03", "anchor": "introduction", "title": "Introduction"}}
{"event": "retrieval_raw", "task_id": "T03", "source": "rubric", "top_k": 0, "model": "sentence-transformers/all-MiniLM-L6-v2"}
{"event": "retrieval_done", "task_id": "T03", "source": "rubric", "kept": 0}
{"event": "retrieval_raw", "task_id": "T03", "source": "assignment", "top_k": 0, "model": "sentence-transformers/all-MiniLM-L6-v2"}
{"event": "retrieval_done", "task_id": "T03", "source": "assignment", "kept": 0}
{"event": "retrieval_raw", "task_id": "T03", "source": "assessment", "top_k": 0, "model": "sentence-transformers/all-MiniLM-L6-v2"}
{"event": "retrieval_done", "task_id": "T03", "source": "assessment", "kept": 0}
{"event": "retrieval_raw", "task_id": "T03", "source": "user", "top_k": 0, "model": "sentence-transformers/all-MiniLM-L6-v2"}
{"event": "retrieval_done", "task_id": "T03", "source": "user", "kept": 0}
{"event": "bundle_done", "task_id": "T03", "rubric": 0, "assignment": 0, "assessment": 0, "user": 0, "consensus": 0}
{"event": "task_meta", "task_id": "T03", "meta": {"id": "T03", "anchor": "introduction", "title": "Introduction"}}
{"event": "retrieval_raw", "task_id": "T03", "source": "rubric", "top_k": 0, "model": "sentence-transformers/all-MiniLM-L6-v2"}
{"event": "retrieval_done", "task_id": "T03", "source": "rubric", "kept": 0}
{"event": "retrieval_raw", "task_id": "T03", "source": "assignment", "top_k": 0, "model": "sentence-transformers/all-MiniLM-L6-v2"}
{"event": "retrieval_done", "task_id": "T03", "source": "assignment", "kept": 0}
{"event": "retrieval_raw", "task_id": "T03", "source": "assessment", "top_k": 0, "model": "sentence-transformers/all-MiniLM-L6-v2"}
{"event": "retrieval_done", "task_id": "T03", "source": "assessment", "kept": 0}
{"event": "retrieval_raw", "task_id": "T03", "source": "user", "top_k": 0, "model": "sentence-transformers/all-MiniLM-L6-v2"}
{"event": "retrieval_done", "task_id": "T03", "source": "user", "kept": 0}
{"event": "bundle_done", "task_id": "T03", "rubric": 0, "assignment": 0, "assessment": 0, "user": 0, "consensus": 0}
{"event": "task_meta", "task_id": "T03", "meta": {"id": "T03", "anchor": "introduction", "title": "Introduction"}}
{"event": "retrieval_raw", "task_id": "T03", "source": "rubric", "top_k": 0, "model": "sentence-transformers/all-MiniLM-L6-v2"}
{"event": "retrieval_done", "task_id": "T03", "source": "rubric", "kept": 0}
{"event": "retrieval_raw", "task_id": "T03", "source": "assignment", "top_k": 0, "model": "sentence-transformers/all-MiniLM-L6-v2"}
{"event": "retrieval_done", "task_id": "T03", "source": "assignment", "kept": 0}
{"event": "retrieval_raw", "task_id": "T03", "source": "assessment", "top_k": 0, "model": "sentence-transformers/all-MiniLM-L6-v2"}
{"event": "retrieval_done", "task_id": "T03", "source": "assessment", "kept": 0}
{"event": "retrieval_raw", "task_id": "T03", "source": "user", "top_k": 0, "model": "sentence-transformers/all-MiniLM-L6-v2"}
{"event": "retrieval_done", "task_id": "T03", "source": "user", "kept": 0}
{"event": "bundle_done", "task_id": "T03", "rubric": 0, "assignment": 0, "assessment": 0, "user": 0, "consensus": 0}
{"event": "task_meta", "task_id": "T03", "meta": {"id": "T03", "anchor": "introduction", "title": "Introduction"}}
{"event": "retrieval_raw", "task_id": "T03", "source": "rubric", "top_k": 0, "model": "sentence-transformers/all-MiniLM-L6-v2"}
{"event": "retrieval_done", "task_id": "T03", "source": "rubric", "kept": 0}
{"event": "retrieval_raw", "task_id": "T03", "source": "assignment", "top_k": 0, "model": "sentence-transformers/all-MiniLM-L6-v2"}
{"event": "retrieval_done", "task_id": "T03", "source": "assignment", "kept": 0}
{"event": "retrieval_raw", "task_id": "T03", "source": "assessment", "top_k": 0, "model": "sentence-transformers/all-MiniLM-L6-v2"}
{"event": "retrieval_done", "task_id": "T03", "source": "assessment", "kept": 0}
{"event": "retrieval_raw", "task_id": "T03", "source": "user", "top_k": 0, "model": "sentence-transformers/all-MiniLM-L6-v2"}
{"event": "retrieval_done", "task_id": "T03", "source": "user", "kept": 0}
{"event": "bundle_done", "task_id": "T03", "rubric": 0, "assignment": 0, "assessment": 0, "user": 0, "consensus": 0}
{"event": "task_meta", "task_id": "T03", "meta": {"id": "T03", "anchor": "introduction", "title": "Introduction"}}
{"event": "retrieval_raw", "task_id": "T03", "source": "rubric", "top_k": 0, "model": "sentence-transformers/all-MiniLM-L6-v2"}
{"event": "retrieval_done", "task_id": "T03", "source": "rubric", "kept": 0}
{"event": "retrieval_raw", "task_id": "T03", "source": "assignment", "top_k": 0, "model": "sentence-transformers/all-MiniLM-L6-v2"}
{"event": "retrieval_done", "task_id": "T03", "source": "assignment", "kept": 0}
{"event": "retrieval_raw", "task_id": "T03", "source": "assessment", "top_k": 0, "model": "sentence-transformers/all-MiniLM-L6-v2"}
{"event": "retrieval_done", "task_id": "T03", "source": "assessment", "kept": 0}
{"event": "retrieval_raw", "task_id": "T03", "source": "user", "top_k": 0, "model": "sentence-transformers/all-MiniLM-L6-v2"}
{"event": "retrieval_done", "task_id": "T03", "source": "user", "kept": 0}
{"event": "bundle_done", "task_id": "T03", "rubric": 0, "assignment": 0, "assessment": 0, "user": 0, "consensus": 0}
{"event": "task_meta", "task_id": "T03", "meta": {"id": "T03", "anchor": "introduction", "title": "Introduction"}}
{"event": "retrieval_raw", "task_id": "T03", "source": "rubric", "top_k": 0, "model": "sentence-transformers/all-MiniLM-L6-v2"}
{"event": "retrieval_done", "task_id": "T03", "source": "rubric", "kept": 0}
{"event": "retrieval_raw", "task_id": "T03", "source": "assignment", "top_k": 0, "model": "sentence-transformers/all-MiniLM-L6-v2"}
{"event": "retrieval_done", "task_id": "T03", "source": "assignment", "kept": 0}
{"event": "retrieval_raw", "task_id": "T03", "source": "assessment", "top_k": 0, "model": "sentence-transformers/all-MiniLM-L6-v2"}
{"event": "retrieval_done", "task_id": "T03", "source": "assessment", "kept": 0}
{"event": "retrieval_raw", "task_id": "T03", "source": "user", "top_k": 0, "model": "sentence-transformers/all-MiniLM-L6-v2"}
{"event": "retrieval_done", "task_id": "T03", "source": "user", "kept": 0}
{"event": "bundle_done", "task_id": "T03", "rubric": 0, "assignment": 0, "assessment": 0, "user": 0, "consensus": 0}
{"event": "task_meta", "task_id": "T03", "meta": {"id": "T03", "anchor": "introduction", "title": "Introduction"}}
{"event": "retrieval_raw", "task_id": "T03", "source": "rubric", "top_k": 0, "model": "sentence-transformers/all-MiniLM-L6-v2"}
{"event": "retrieval_done", "task_id": "T03", "source": "rubric", "kept": 0}
{"event": "retrieval_raw", "task_id": "T03", "source": "assignment", "top_k": 0, "model": "sentence-transformers/all-MiniLM-L6-v2"}
{"event": "retrieval_done", "task_id": "T03", "source": "assignment", "kept": 0}
{"event": "retrieval_raw", "task_id": "T03", "source": "assessment", "top_k": 0, "model": "sentence-transformers/all-MiniLM-L6-v2"}
{"event": "retrieval_done", "task_id": "T03", "source": "assessment", "kept": 0}
{"event": "retrieval_raw", "task_id": "T03", "source": "user", "top_k": 0, "model": "sentence-transformers/all-MiniLM-L6-v2"}
{"event": "retrieval_done", "task_id": "T03", "source": "user", "kept": 0}
{"event": "bundle_done", "task_id": "T03", "rubric": 0, "assignment": 0, "assessment": 0, "user": 0, "consensus": 0}
{"event": "task_meta", "task_id": "T03", "meta": {"id": "T03", "anchor": "introduction", "title": "Introduction"}}
{"event": "retrieval_raw", "task_id": "T03", "source": "rubric", "top_k": 0, "model": "sentence-transformers/all-MiniLM-L6-v2"}
{"event": "retrieval_done", "task_id": "T03", "source": "rubric", "kept": 0}
{"event": "retrieval_raw", "task_id": "T03", "source": "assignment", "top_k": 0, "model": "sentence-transformers/all-MiniLM-L6-v2"}
{"event": "retrieval_done", "task_id": "T03", "source": "assignment", "kept": 0}
{"event": "retrieval_raw", "task_id": "T03", "source": "assessment", "top_k": 0, "model": "sentence-transformers/all-MiniLM-L6-v2"}
{"event": "retrieval_done", "task_id": "T03", "source": "assessment", "kept": 0}
{"event": "retrieval_raw", "task_id": "T03", "source": "user", "top_k": 0, "model": "sentence-transformers/all-MiniLM-L6-v2"}
{"event": "retrieval_done", "task_id": "T03", "source": "user", "kept": 0}
{"event": "bundle_done", "task_id": "T03", "rubric": 0, "assignment": 0, "assessment": 0, "user": 0, "consensus": 0}
{"event": "task_meta", "task_id": "T03", "meta": {"id": "T03", "anchor": "introduction", "title": "Introduction"}}
{"event": "retrieval_raw", "task_id": "T03", "source": "rubric", "top_k": 0, "model": "sentence-transformers/all-MiniLM-L6-v2"}
{"event": "retrieval_done", "task_id": "T03", "source": "rubric", "kept": 0}
{"event": "retrieval_raw", "task_id": "T03", "source": "assignment", "top_k": 0, "model": "sentence-transformers/all-MiniLM-L6-v2"}
{"event": "retrieval_done", "task_id": "T03", "source": "assignment", "kept": 0}
{"event": "retrieval_raw", "task_id": "T03", "source": "assessment", "top_k": 0, "model": "sentence-transformers/all-MiniLM-L6-v2"}
{"event": "retrieval_done", "task_id": "T03", "source": "assessment", "kept": 0}
{"event": "retrieval_raw", "task_id": "T03", "source": "user", "top_k": 0, "model": "sentence-transformers/all-MiniLM-L6-v2"}
{"event": "retrieval_done", "task_id": "T03", "source": "user", "kept": 0}
{"event": "bundle_done", "task_id": "T03", "rubric": 0, "assignment": 0, "assessment": 0, "user": 0, "consensus": 0}
{"event": "task_meta", "task_id": "T03", "meta": {"id": "T03", "anchor": "introduction", "title": "Introduction"}}
{"event": "retrieval_raw", "task_id": "T03", "source": "rubric", "top_k": 0, "model": "sentence-transformers/all-MiniLM-L6-v2"}
{"event": "retrieval_done", "task_id": "T03", "source": "rubric", "kept": 0}
{"event": "retrieval_raw", "task_id": "T03", "source": "assignment", "top_k": 0, "model": "sentence-transformers/all-MiniLM-L6-v2"}
{"event": "retrieval_done", "task_id": "T03", "source": "assignment", "kept": 0}
{"event": "retrieval_raw", "task_id": "T03", "source": "assessment", "top_k": 0, "model": "sentence-transformers/all-MiniLM-L6-v2"}
{"event": "retrieval_done", "task_id": "T03", "source": "assessment", "kept": 0}
{"event": "retrieval_raw", "task_id": "T03", "source": "user", "top_k": 0, "model": "sentence-transformers/all-MiniLM-L6-v2"}
{"event": "retrieval_done", "task_id": "T03", "source": "user", "kept": 0}
{"event": "bundle_done", "task_id": "T03", "rubric": 0, "assignment": 0, "assessment": 0, "user": 0, "consensus": 0}
