{
  "name": "Visual-TableQA",
  "slug": "visual-tableqa",
  "tracks": [
    "T4",
    "T5",
    "T6"
  ],
  "url": "https://github.com/AI-4-Everyone/Visual-TableQA",
  "license": "Unknown",
  "storage": {
    "raw_root": "training_data/raw/visual-tableqa",
    "processed_root": "training_data/processed/visual-tableqa",
    "modalities": [
      {
        "modality": "page-image",
        "path": "training_data/raw/visual-tableqa/images"
      },
      {
        "modality": "latex-src",
        "path": "training_data/raw/visual-tableqa/latex"
      }
    ]
  },
  "ingest": {
    "strategy": "git",
    "command": "git clone https://github.com/AI-4-Everyone/Visual-TableQA \"training_data/raw/visual-tableqa/source\"",
    "needs_auth": false,
    "notes": []
  },
  "preprocess": [
    "Use LaTeX source for precise structure, render to image",
    "Leverage QA pairs for joint table and reasoning tasks"
  ],
  "strengths": [
    "Open-domain, complex tables",
    "Reasoning-intensive QA pairs",
    "Low generation cost"
  ],
  "limitations": [
    "License needs verification",
    "Synthetic data",
    "Moderate scale"
  ],
  "modality": [
    "page-image",
    "latex-src"
  ],
  "domain": [
    "scientific"
  ],
  "is_synthetic": true,
  "languages": [
    "en"
  ],
  "size": {
    "images": 2500,
    "pages": null,
    "pdfs": null,
    "qa_pairs": 6000
  },
  "relevance": 0.8,
  "justification": "Covers table detection/structure (T4), chart/diagram understanding via visual QA (T5), and document QA (T6) on complex table images."
}
